{
  "$schema": "https://ui.shadcn.com/schema/registry-item.json",
  "name": "all",
  "type": "registry:ui",
  "dependencies": [],
  "devDependencies": [],
  "registryDependencies": [
    "@glitchcn/globals",
    "@glitchcn/accordion",
    "@glitchcn/alert",
    "@glitchcn/badge",
    "@glitchcn/button",
    "@glitchcn/card",
    "@glitchcn/checkbox",
    "@glitchcn/collapsible",
    "@glitchcn/command",
    "@glitchcn/corner-brackets",
    "@glitchcn/dialog",
    "@glitchcn/input-otp",
    "@glitchcn/input",
    "@glitchcn/progress",
    "@glitchcn/scanline-overlay",
    "@glitchcn/separator",
    "@glitchcn/sheet",
    "@glitchcn/sidebar",
    "@glitchcn/skeleton",
    "@glitchcn/spinner",
    "@glitchcn/table",
    "@glitchcn/tabs",
    "@glitchcn/theme-switcher",
    "@glitchcn/tooltip"
  ],
  "files": []
}